{
  "schema_version": 1,
  "generated_at": "2026-06-13T18:13:08.030664+08:00",
  "date": "2026-06-13",
  "crawl_time": "18-13",
  "counts": {
    "total": 21,
    "news": 21,
    "rss": 0
  },
  "items": [
    {
      "id": "news:41",
      "t": "这4个社保谣言 你能识破吗",
      "cat": "社会保障",
      "src": "百度热搜",
      "rank": 11,
      "url": "https://www.baidu.com/s?wd=%E8%BF%994%E4%B8%AA%E7%A4%BE%E4%BF%9D%E8%B0%A3%E8%A8%80+%E4%BD%A0%E8%83%BD%E8%AF%86%E7%A0%B4%E5%90%97",
      "time": "18-13",
      "latest": true,
      "type": "news"
    },
    {
      "id": "news:113",
      "t": "UP主深度还原高考三天",
      "cat": "教育民生",
      "src": "bilibili 热搜",
      "rank": 23,
      "url": "https://search.bilibili.com/all?keyword=UP%E4%B8%BB%E6%B7%B1%E5%BA%A6%E8%BF%98%E5%8E%9F%E9%AB%98%E8%80%83%E4%B8%89%E5%A4%A9",
      "time": "18-13",
      "latest": true,
      "type": "news"
    },
    {
      "id": "news:118",
      "t": "校园末日降临",
      "cat": "教育民生",
      "src": "bilibili 热搜",
      "rank": 28,
      "url": "https://search.bilibili.com/all?keyword=%E6%A0%A1%E5%9B%AD%E6%9C%AB%E6%97%A5%E9%99%8D%E4%B8%B4",
      "time": "18-13",
      "latest": true,
      "type": "news"
    },
    {
      "id": "news:133",
      "t": "美国消费者信心从历史低位反弹 汽油价格回落带来喘息空间",
      "cat": "物价消费",
      "src": "财联社热门",
      "rank": 13,
      "url": "https://www.cls.cn/detail/2398882",
      "time": "18-13",
      "latest": true,
      "type": "news"
    },
    {
      "id": "news:208",
      "t": "今天是文化和自然遗产日",
      "cat": "人口家庭",
      "src": "抖音",
      "rank": 3,
      "url": "https://www.douyin.com/hot/2532925",
      "time": "18-13",
      "latest": true,
      "type": "news"
    },
    {
      "id": "news:231",
      "t": "南极半岛出现异常高温",
      "cat": "安全灾害",
      "src": "抖音",
      "rank": 26,
      "url": "https://www.douyin.com/hot/2533017",
      "time": "18-13",
      "latest": true,
      "type": "news"
    },
    {
      "id": "news:144",
      "t": "特朗普：美军打死“阿拉瓜火车”组织首领",
      "cat": "交通出行",
      "src": "凤凰网",
      "rank": 11,
      "url": "https://news.ifeng.com/c/8tuxrPNiEYB",
      "time": "18-13",
      "latest": true,
      "type": "news"
    },
    {
      "id": "news:72",
      "t": "贵州锦屏通报大学生因腹泻入院后死亡：医院存在医疗过错，已启动调解",
      "cat": "医疗健康",
      "src": "澎湃新闻",
      "rank": 2,
      "url": "https://m.thepaper.cn/newsDetail_forward_33368905",
      "time": "18-13",
      "latest": true,
      "type": "news"
    },
    {
      "id": "news:90",
      "t": "不写论文也能拿学位？首批实践毕业生：用小说、商业项目其实更难",
      "cat": "就业民生",
      "src": "澎湃新闻",
      "rank": 20,
      "url": "https://m.thepaper.cn/newsDetail_forward_33373040",
      "time": "18-13",
      "latest": true,
      "type": "news"
    },
    {
      "id": "news:158",
      "t": "精明家长,高考分数=手机价格",
      "cat": "教育民生",
      "src": "贴吧",
      "rank": 13,
      "url": "https://tieba.baidu.com/hottopic/browse/hottopic?amp%3Btopic_name=%E7%B2%BE%E6%98%8E%E5%AE%B6%E9%95%BF%2C%E9%AB%98%E8%80%83%E5%88%86%E6%95%B0%3D%E6%89%8B%E6%9C%BA%E4%BB%B7%E6%A0%BC&topic_id=28355109",
      "time": "18-13",
      "latest": true,
      "type": "news"
    },
    {
      "id": "news:160",
      "t": "女子点外卖离奇收到活牛蛙",
      "cat": "交通出行",
      "src": "贴吧",
      "rank": 15,
      "url": "https://tieba.baidu.com/hottopic/browse/hottopic?amp%3Btopic_name=%E5%A5%B3%E5%AD%90%E7%82%B9%E5%A4%96%E5%8D%96%E7%A6%BB%E5%A5%87%E6%94%B6%E5%88%B0%E6%B4%BB%E7%89%9B%E8%9B%99&topic_id=28355111",
      "time": "18-13",
      "latest": true,
      "type": "news"
    },
    {
      "id": "news:174",
      "t": "冲!高考考生许愿LPL夺冠",
      "cat": "教育民生",
      "src": "贴吧",
      "rank": 29,
      "url": "https://tieba.baidu.com/hottopic/browse/hottopic?amp%3Btopic_name=%E5%86%B2%21%E9%AB%98%E8%80%83%E8%80%83%E7%94%9F%E8%AE%B8%E6%84%BFLPL%E5%A4%BA%E5%86%A0&topic_id=28355074",
      "time": "18-13",
      "latest": true,
      "type": "news"
    },
    {
      "id": "news:11",
      "t": "湖北洪水冲断桥梁系谣言",
      "cat": "安全灾害",
      "src": "今日头条",
      "rank": 11,
      "url": "https://www.toutiao.com/trending/7650466764858998794/",
      "time": "18-13",
      "latest": true,
      "type": "news"
    },
    {
      "id": "news:17",
      "t": "全国名中医单兆伟去世",
      "cat": "中医养生",
      "src": "今日头条",
      "rank": 17,
      "url": "https://www.toutiao.com/trending/7650481384046460991/",
      "time": "18-13",
      "latest": true,
      "type": "news"
    },
    {
      "id": "news:18",
      "t": "过路大爷暴雨前1秒帮户主盖好小麦",
      "cat": "安全灾害",
      "src": "今日头条",
      "rank": 18,
      "url": "https://www.toutiao.com/trending/7650488923621982262/",
      "time": "18-13",
      "latest": true,
      "type": "news"
    },
    {
      "id": "news:24",
      "t": "农村女孩高考结束帮父母收麦子",
      "cat": "教育民生",
      "src": "今日头条",
      "rank": 24,
      "url": "https://www.toutiao.com/trending/7649745776301588490/",
      "time": "18-13",
      "latest": true,
      "type": "news"
    },
    {
      "id": "news:28",
      "t": "高考结束男生拿着一桶一行囊独自回家",
      "cat": "教育民生",
      "src": "今日头条",
      "rank": 28,
      "url": "https://www.toutiao.com/trending/7649728185214926894/",
      "time": "18-13",
      "latest": true,
      "type": "news"
    },
    {
      "id": "news:69",
      "t": "报道：美伊将在下周G7会议前后达成和平协议，油价重挫",
      "cat": "物价消费",
      "src": "华尔街见闻",
      "rank": 9,
      "url": "https://wallstreetcn.com/articles/3774526",
      "time": "18-13",
      "latest": true,
      "type": "news"
    },
    {
      "id": "news:179",
      "t": "帅氏药膳鸡",
      "cat": "中医养生",
      "src": "微博",
      "rank": 4,
      "url": "https://s.weibo.com/weibo?q=%E5%B8%85%E6%B0%8F%E8%8D%AF%E8%86%B3%E9%B8%A1&t=31&band_rank=4&Refer=top",
      "time": "18-13",
      "latest": true,
      "type": "news"
    },
    {
      "id": "news:237",
      "t": "日本炸鸡店称一锅油反复用 66 年，从食品安全和健康角度看，这种做法存在哪些潜在风险？",
      "cat": "食品安全",
      "src": "知乎",
      "rank": 2,
      "url": "https://www.zhihu.com/question/2048692040377033581",
      "time": "18-13",
      "latest": true,
      "type": "news"
    },
    {
      "id": "news:243",
      "t": "网传一大厂裁员后 bug 无人修复，靠虚假招聘骗修复方案，如何看待这一操作？",
      "cat": "就业民生",
      "src": "知乎",
      "rank": 8,
      "url": "https://www.zhihu.com/question/2047628590754133157",
      "time": "18-13",
      "latest": true,
      "type": "news"
    }
  ]
}