{
  "schema_version": 1,
  "generated_at": "2026-06-25T05:54:37.121421+08:00",
  "date": "2026-06-25",
  "crawl_time": "05-54",
  "counts": {
    "total": 31,
    "news": 31,
    "rss": 0
  },
  "items": [
    {
      "id": "news:40",
      "t": "2026年各地高考分数线汇总",
      "cat": "教育民生",
      "src": "百度热搜",
      "rank": 10,
      "url": "https://www.baidu.com/s?wd=2026%E5%B9%B4%E5%90%84%E5%9C%B0%E9%AB%98%E8%80%83%E5%88%86%E6%95%B0%E7%BA%BF%E6%B1%87%E6%80%BB",
      "time": "05-54",
      "latest": true,
      "type": "news"
    },
    {
      "id": "news:42",
      "t": "河南2026年高考分数线公布",
      "cat": "教育民生",
      "src": "百度热搜",
      "rank": 12,
      "url": "https://www.baidu.com/s?wd=%E6%B2%B3%E5%8D%972026%E5%B9%B4%E9%AB%98%E8%80%83%E5%88%86%E6%95%B0%E7%BA%BF%E5%85%AC%E5%B8%83",
      "time": "05-54",
      "latest": true,
      "type": "news"
    },
    {
      "id": "news:44",
      "t": "校长与教师婚外情买假结婚证生两孩",
      "cat": "人口家庭",
      "src": "百度热搜",
      "rank": 14,
      "url": "https://www.baidu.com/s?wd=%E6%A0%A1%E9%95%BF%E4%B8%8E%E6%95%99%E5%B8%88%E5%A9%9A%E5%A4%96%E6%83%85%E4%B9%B0%E5%81%87%E7%BB%93%E5%A9%9A%E8%AF%81%E7%94%9F%E4%B8%A4%E5%AD%A9",
      "time": "05-54",
      "latest": true,
      "type": "news"
    },
    {
      "id": "news:50",
      "t": "高考查分",
      "cat": "教育民生",
      "src": "百度热搜",
      "rank": 20,
      "url": "https://www.baidu.com/s?wd=%E9%AB%98%E8%80%83%E6%9F%A5%E5%88%86",
      "time": "05-54",
      "latest": true,
      "type": "news"
    },
    {
      "id": "news:97",
      "t": "沉浸式高考查分",
      "cat": "教育民生",
      "src": "bilibili 热搜",
      "rank": 7,
      "url": "https://search.bilibili.com/all?keyword=%E6%B2%89%E6%B5%B8%E5%BC%8F%E9%AB%98%E8%80%83%E6%9F%A5%E5%88%86",
      "time": "05-54",
      "latest": true,
      "type": "news"
    },
    {
      "id": "news:101",
      "t": "2026高考分数线",
      "cat": "教育民生",
      "src": "bilibili 热搜",
      "rank": 11,
      "url": "https://search.bilibili.com/all?keyword=2026%E9%AB%98%E8%80%83%E5%88%86%E6%95%B0%E7%BA%BF",
      "time": "05-54",
      "latest": true,
      "type": "news"
    },
    {
      "id": "news:115",
      "t": "记录高考查分瞬间",
      "cat": "教育民生",
      "src": "bilibili 热搜",
      "rank": 25,
      "url": "https://search.bilibili.com/all?keyword=%E8%AE%B0%E5%BD%95%E9%AB%98%E8%80%83%E6%9F%A5%E5%88%86%E7%9E%AC%E9%97%B4",
      "time": "05-54",
      "latest": true,
      "type": "news"
    },
    {
      "id": "news:206",
      "t": "我的高考出分时刻",
      "cat": "教育民生",
      "src": "抖音",
      "rank": 1,
      "url": "https://www.douyin.com/hot/2545334",
      "time": "05-54",
      "latest": true,
      "type": "news"
    },
    {
      "id": "news:207",
      "t": "晒晒我的高考成绩",
      "cat": "教育民生",
      "src": "抖音",
      "rank": 2,
      "url": "https://www.douyin.com/hot/2546557",
      "time": "05-54",
      "latest": true,
      "type": "news"
    },
    {
      "id": "news:213",
      "t": "中考后的第一条抖音",
      "cat": "教育民生",
      "src": "抖音",
      "rank": 8,
      "url": "https://www.douyin.com/hot/2545604",
      "time": "05-54",
      "latest": true,
      "type": "news"
    },
    {
      "id": "news:215",
      "t": "如果我来写各省中考作文",
      "cat": "教育民生",
      "src": "抖音",
      "rank": 10,
      "url": "https://www.douyin.com/hot/2545745",
      "time": "05-54",
      "latest": true,
      "type": "news"
    },
    {
      "id": "news:226",
      "t": "河南高考分数线公布",
      "cat": "教育民生",
      "src": "抖音",
      "rank": 21,
      "url": "https://www.douyin.com/hot/2546471",
      "time": "05-54",
      "latest": true,
      "type": "news"
    },
    {
      "id": "news:136",
      "t": "特朗普对石油公司开刀：下令调查哄抬行为，称油价已断崖式下跌",
      "cat": "物价消费",
      "src": "凤凰网",
      "rank": 3,
      "url": "https://news.ifeng.com/c/8uDgRGX21RF",
      "time": "05-54",
      "latest": true,
      "type": "news"
    },
    {
      "id": "news:144",
      "t": "内蒙古多地有人夜放烟花庆祝高考放榜，被指影响中考",
      "cat": "教育民生",
      "src": "凤凰网",
      "rank": 11,
      "url": "https://news.ifeng.com/c/8uDqtc9O8OL",
      "time": "05-54",
      "latest": true,
      "type": "news"
    },
    {
      "id": "news:74",
      "t": "空空荡荡的公交车，如何跑出时代的岔路口",
      "cat": "交通出行",
      "src": "澎湃新闻",
      "rank": 4,
      "url": "https://m.thepaper.cn/newsDetail_forward_33426468",
      "time": "05-54",
      "latest": true,
      "type": "news"
    },
    {
      "id": "news:80",
      "t": "欧洲遭遇“更早、更久、更难解”的高温：蝙蝠热死，40人为躲热浪溺亡",
      "cat": "安全灾害",
      "src": "澎湃新闻",
      "rank": 10,
      "url": "https://m.thepaper.cn/newsDetail_forward_33442618",
      "time": "05-54",
      "latest": true,
      "type": "news"
    },
    {
      "id": "news:88",
      "t": "持续更新丨各省份高考分数线陆续公布",
      "cat": "教育民生",
      "src": "澎湃新闻",
      "rank": 18,
      "url": "https://m.thepaper.cn/newsDetail_forward_33442245",
      "time": "05-54",
      "latest": true,
      "type": "news"
    },
    {
      "id": "news:146",
      "t": "高考分数出炉,考生集体报喜",
      "cat": "教育民生",
      "src": "贴吧",
      "rank": 1,
      "url": "https://tieba.baidu.com/hottopic/browse/hottopic?amp%3Btopic_name=%E9%AB%98%E8%80%83%E5%88%86%E6%95%B0%E5%87%BA%E7%82%89%2C%E8%80%83%E7%94%9F%E9%9B%86%E4%BD%93%E6%8A%A5%E5%96%9C&topic_id=28355606",
      "time": "05-54",
      "latest": true,
      "type": "news"
    },
    {
      "id": "news:156",
      "t": "货架被狗尿,保洁阿姨压力大",
      "cat": "睡眠心理",
      "src": "贴吧",
      "rank": 11,
      "url": "https://tieba.baidu.com/hottopic/browse/hottopic?amp%3Btopic_name=%E8%B4%A7%E6%9E%B6%E8%A2%AB%E7%8B%97%E5%B0%BF%2C%E4%BF%9D%E6%B4%81%E9%98%BF%E5%A7%A8%E5%8E%8B%E5%8A%9B%E5%A4%A7&topic_id=28355621",
      "time": "05-54",
      "latest": true,
      "type": "news"
    },
    {
      "id": "news:161",
      "t": "急哭!吧友坐等高考出分",
      "cat": "教育民生",
      "src": "贴吧",
      "rank": 16,
      "url": "https://tieba.baidu.com/hottopic/browse/hottopic?amp%3Btopic_name=%E6%80%A5%E5%93%AD%21%E5%90%A7%E5%8F%8B%E5%9D%90%E7%AD%89%E9%AB%98%E8%80%83%E5%87%BA%E5%88%86&topic_id=28355591",
      "time": "05-54",
      "latest": true,
      "type": "news"
    },
    {
      "id": "news:5",
      "t": "“关岛快递”东风-26首次裸弹亮相",
      "cat": "交通出行",
      "src": "今日头条",
      "rank": 5,
      "url": "https://www.toutiao.com/trending/7654942875204980260/",
      "time": "05-54",
      "latest": true,
      "type": "news"
    },
    {
      "id": "news:10",
      "t": "校长与教师婚外情买假结婚证生两孩",
      "cat": "人口家庭",
      "src": "今日头条",
      "rank": 10,
      "url": "https://www.toutiao.com/trending/7654916576543096895/",
      "time": "05-54",
      "latest": true,
      "type": "news"
    },
    {
      "id": "news:12",
      "t": "高考707分考生分享学习方法",
      "cat": "教育民生",
      "src": "今日头条",
      "rank": 12,
      "url": "https://www.toutiao.com/trending/7654422387446202387/",
      "time": "05-54",
      "latest": true,
      "type": "news"
    },
    {
      "id": "news:19",
      "t": "河南高考分数线公布",
      "cat": "教育民生",
      "src": "今日头条",
      "rank": 19,
      "url": "https://www.toutiao.com/trending/7654783511912169510/",
      "time": "05-54",
      "latest": true,
      "type": "news"
    },
    {
      "id": "news:30",
      "t": "为什么建议35岁就开始控糖",
      "cat": "营养饮食",
      "src": "今日头条",
      "rank": 30,
      "url": "https://www.toutiao.com/trending/7654451167083348011/",
      "time": "05-54",
      "latest": true,
      "type": "news"
    },
    {
      "id": "news:68",
      "t": "英伟达要求PCB厂商降价10%？记者求证",
      "cat": "物价消费",
      "src": "华尔街见闻",
      "rank": 8,
      "url": "https://wallstreetcn.com/articles/3775353",
      "time": "05-54",
      "latest": true,
      "type": "news"
    },
    {
      "id": "news:178",
      "t": "世界最快高铁跑出中国创新加速度",
      "cat": "交通出行",
      "src": "微博",
      "rank": 3,
      "url": "https://s.weibo.com/weibo?q=%23%E4%B8%96%E7%95%8C%E6%9C%80%E5%BF%AB%E9%AB%98%E9%93%81%E8%B7%91%E5%87%BA%E4%B8%AD%E5%9B%BD%E5%88%9B%E6%96%B0%E5%8A%A0%E9%80%9F%E5%BA%A6%23&t=31&band_rank=3&Refer=top",
      "time": "05-54",
      "latest": true,
      "type": "news"
    },
    {
      "id": "news:195",
      "t": "河南高考分数线",
      "cat": "教育民生",
      "src": "微博",
      "rank": 20,
      "url": "https://s.weibo.com/weibo?q=%E6%B2%B3%E5%8D%97%E9%AB%98%E8%80%83%E5%88%86%E6%95%B0%E7%BA%BF&t=31&band_rank=20&Refer=top",
      "time": "05-54",
      "latest": true,
      "type": "news"
    },
    {
      "id": "news:201",
      "t": "37岁教师身体不适坚持上课心梗去世",
      "cat": "常见疾病",
      "src": "微博",
      "rank": 26,
      "url": "https://s.weibo.com/weibo?q=%2337%E5%B2%81%E6%95%99%E5%B8%88%E8%BA%AB%E4%BD%93%E4%B8%8D%E9%80%82%E5%9D%9A%E6%8C%81%E4%B8%8A%E8%AF%BE%E5%BF%83%E6%A2%97%E5%8E%BB%E4%B8%96%23&t=31&band_rank=26&Refer=top",
      "time": "05-54",
      "latest": true,
      "type": "news"
    },
    {
      "id": "news:239",
      "t": "家长发愁孩子高考后消费账单，一句「你只是高考完了，不是家里发财了」引发共鸣，如何看待这一说法？",
      "cat": "教育民生",
      "src": "知乎",
      "rank": 4,
      "url": "https://www.zhihu.com/question/2052870237394149872",
      "time": "05-54",
      "latest": true,
      "type": "news"
    },
    {
      "id": "news:245",
      "t": "如何看待 41 岁 C 罗生物年龄仅 28.9 岁，他的食谱永远只有鸡肉、鱼类、蔬菜？普通人效仿可能面临哪些风险？",
      "cat": "日常饮食",
      "src": "知乎",
      "rank": 10,
      "url": "https://www.zhihu.com/question/2053054134677239570",
      "time": "05-54",
      "latest": true,
      "type": "news"
    }
  ]
}